cy_widgets/__init__.py
cy_widgets/cli.py
cy_widgets/backtest/__init__.py
cy_widgets/backtest/helper.py
cy_widgets/backtest/strategy.py
cy_widgets/charts/__init__.py
cy_widgets/charts/pyecharts.py
cy_widgets/exchange/__init__.py
cy_widgets/exchange/order.py
cy_widgets/exchange/provider.py
cy_widgets/exchange/signal.py
cy_widgets/fetcher/__init__.py
cy_widgets/fetcher/exchange.py
cy_widgets/logger/__init__.py
cy_widgets/logger/base.py
cy_widgets/logger/trading.py
cy_widgets/neutral/__init__.py
cy_widgets/neutral/neutral_indicators.py
cy_widgets/strategy/__init__.py
cy_widgets/strategy/evaluation.py
cy_widgets/strategy/position.py
cy_widgets/strategy/exchange/__init__.py
cy_widgets/strategy/exchange/aberration_flash_bolling.py
cy_widgets/strategy/exchange/aims.py
cy_widgets/strategy/exchange/autobuy.py
cy_widgets/strategy/exchange/base.py
cy_widgets/strategy/exchange/bolling.py
cy_widgets/strategy/exchange/ice_ma_shrinkage.py
cy_widgets/strategy/exchange/mtm_adapt_bolling.py
cy_widgets/strategy/exchange/rsi.py
cy_widgets/strategy/exchange/sb_atr_bolling.py
cy_widgets/strategy/exchange/sb_ma_gap_bolling.py
cy_widgets/strategy/exchange/stop_win_bolling.py
cy_widgets/strategy/exchange/vix_bolling.py
cy_widgets/strategy/neutral/__init__.py
cy_widgets/strategy/neutral/base.py
cy_widgets/strategy/neutral/binance_neutral.py
cy_widgets/trader/__init__.py
cy_widgets/trader/exchange_order_exec.py
cy_widgets/trader/exchange_trader.py
cy_widgets-0.4.36.dist-info/LICENSE
cy_widgets-0.4.36.dist-info/METADATA
cy_widgets-0.4.36.dist-info/WHEEL
cy_widgets-0.4.36.dist-info/entry_points.txt
cy_widgets-0.4.36.dist-info/top_level.txt
cy_widgets-0.4.36.dist-info/RECORD
